wander/__init__.py
wander/models.py
wander/plugins/__init__.py
wander/plugins/clipboard.py
wander/plugins/shell.py
wander/render.py
wander/utils.py
wander-0.1.1.dist-info/LICENSE.md
wander-0.1.1.dist-info/METADATA
wander-0.1.1.dist-info/WHEEL
wander-0.1.1.dist-info/RECORD
