Metadata-Version: 2.1
Name: wander
Version: 0.1.1
Summary: 
Home-page: https://github.com/outday29/wander
License: MIT
Author: engkheng
Author-email: ongengkheng929@gmail.com
Requires-Python: >=3.10,<4.0
Classifier: License :: OSI Approved :: MIT License
Classifier: Programming Language :: Python :: 3
Classifier: Programming Language :: Python :: 3.10
Classifier: Programming Language :: Python :: 3.11
Requires-Dist: pydantic (>=1.10.7,<2.0.0)
Project-URL: Repository, https://github.com/outday29/wander
